aigarth_it/__init__.py
aigarth_it/_version.py
aigarth_it/bak/aitu_cl_bak.py
aigarth_it/bak/icm.py.bak
aigarth_it/common.py
aigarth_it/dataset.py
aigarth_it/exceptions.py
aigarth_it/icap/__init__.py
aigarth_it/icap/common.py
aigarth_it/icap/itucl_aai_i2x7o8.py
aigarth_it/itu_base.py
aigarth_it/itu_cl.py
aigarth_it/itu_perf.py
aigarth_it/neuron_cl.py
aigarth_it/sandbox/constant_hierarchy.py
aigarth_it/sandbox/enum_example.py
aigarth_it-0.1.0.dist-info/LICENSE
aigarth_it-0.1.0.dist-info/METADATA
aigarth_it-0.1.0.dist-info/WHEEL
aigarth_it-0.1.0.dist-info/RECORD
