Metadata-Version: 2.3
Name: aigarth-it
Version: 0.1.0
Summary: Aigarth Intelligent Tissue
License: Aigarth
Keywords: Aigarth,AI
Author: ambient@mailbox.org
Requires-Python: >=3.11
Classifier: Development Status :: 4 - Beta
Classifier: License :: Other/Proprietary License
Classifier: Operating System :: POSIX :: Linux
Classifier: Programming Language :: Python :: 3
Classifier: Programming Language :: Python :: 3.11
Classifier: Programming Language :: Python :: 3.12
Classifier: Programming Language :: Python :: Implementation :: CPython
Classifier: Topic :: Scientific/Engineering
Classifier: Topic :: Scientific/Engineering :: Artificial Intelligence
Classifier: Topic :: Scientific/Engineering :: Artificial Life
Classifier: Topic :: Software Development :: Libraries
Classifier: Intended Audience :: Developers
Classifier: Intended Audience :: Science/Research
Requires-Dist: packaging (>=25.0,<26.0)
Requires-Dist: pydantic (>=2.11.7,<3.0.0)
Requires-Dist: sqlite-construct (>=0,<1)
Requires-Dist: sqlite-kvdb (>=0,<1)
Project-URL: Repository, https://github.com/aigarth/aigarth-it
